traversify/__init__.py
traversify/metadata.py
traversify/tests.py
traversify/traverser.py
traversify-1.1.2.dist-info/AUTHORS
traversify-1.1.2.dist-info/LICENSE
traversify-1.1.2.dist-info/METADATA
traversify-1.1.2.dist-info/WHEEL
traversify-1.1.2.dist-info/top_level.txt
traversify-1.1.2.dist-info/RECORD
