Metadata-Version: 2.1
Name: traversify
Version: 1.1.2
Summary: Handy python classes for manipulating json data, providing syntactic sugar for less verbose, easier to write code.
Home-page: https://github.com/aelkner/traversify
Author: Alan Elkner
Author-email: aelkner@gmail.com
License: GNU GENERAL PUBLIC LICENSE version 3
Platform: UNKNOWN
